numcodecs_safeguards/__init__.py
numcodecs_safeguards/checksum.py
numcodecs_safeguards/compute.py
numcodecs_safeguards/lossless.py
numcodecs_safeguards/py.typed
numcodecs_safeguards-0.1.0b1.dist-info/METADATA
numcodecs_safeguards-0.1.0b1.dist-info/WHEEL
numcodecs_safeguards-0.1.0b1.dist-info/entry_points.txt
numcodecs_safeguards-0.1.0b1.dist-info/licenses/LICENSE
numcodecs_safeguards-0.1.0b1.dist-info/RECORD
